{
  "started_at": "2026-06-04T17:30:56",
  "cryptos": [
    {
      "symbol": "SOL-USD",
      "slug": "sol",
      "points": 366,
      "return_pct": -54.6
    },
    {
      "symbol": "XMR-USD",
      "slug": "xmr",
      "points": 366,
      "return_pct": 10.6
    },
    {
      "symbol": "HYPE32196-USD",
      "slug": "hype",
      "points": 365,
      "return_pct": 88.3
    },
    {
      "symbol": "BTC-USD",
      "slug": "btc",
      "points": 366,
      "return_pct": -39.0
    },
    {
      "symbol": "TRX-USD",
      "slug": "trx",
      "points": 366,
      "return_pct": 22.2
    }
  ],
  "errors": [],
  "finished_at": "2026-06-04T17:31:12"
}